setup.py
tests/__init__.py
tests/test.py
toml_python.egg-info/PKG-INFO
toml_python.egg-info/SOURCES.txt
toml_python.egg-info/dependency_links.txt
toml_python.egg-info/top_level.txt
tomlpython/__init__.py
tomlpython/parser.py
tomlpython/reader.py