Metadata-Version: 1.1
Name: toml-python
Version: 0.3
Summary: TOML parser for python.
Home-page: https://github.com/f03lipe/toml-python
Author: Felipe Aragão Pires
Author-email: pires.a.felipe@gmail.com
License: MIT License
Platform: UNKNOWN
Classifier: Development Status :: 2 - Pre-Alpha
Classifier: Intended Audience :: Developers
Classifier: License :: OSI Approved :: MIT License
Classifier: Programming Language :: Python :: 3
